epist/__init__.py
epist_sdk-0.1.0.dist-info/METADATA
epist_sdk-0.1.0.dist-info/WHEEL
epist_sdk-0.1.0.dist-info/RECORD
