Metadata-Version: 2.4
Name: epist-sdk
Version: 0.1.0
Summary: Official Python SDK for Epist.ai
Project-URL: Homepage, https://epist.ai
Project-URL: Repository, https://github.com/epist-ai/epist-sdk-python
Author-email: Epist Team <support@epist.ai>
Requires-Python: >=3.8
Requires-Dist: httpx>=0.24.0
